mastercard_locations-1.0.5.dist-info/DESCRIPTION.rst
mastercard_locations-1.0.5.dist-info/METADATA
mastercard_locations-1.0.5.dist-info/RECORD
mastercard_locations-1.0.5.dist-info/WHEEL
mastercard_locations-1.0.5.dist-info/metadata.json
mastercard_locations-1.0.5.dist-info/top_level.txt
mastercardlocations/__init__.py
mastercardlocations/atmcountries.py
mastercardlocations/atmcountrysubdivisions.py
mastercardlocations/atmlocations.py
mastercardlocations/merchantcategories.py
mastercardlocations/merchantcountries.py
mastercardlocations/merchantcountrysubdivisions.py
mastercardlocations/merchantlocations.py
mastercardlocations/resourceconfig.py
